xseof/__init__.py
xseof/aux_orbdop/__init__.py
xseof/aux_orbdop/eo_oper_aux_orbdop_0100.py
xseof/aux_orbdop/eo_oper_aux_orbdop_0101.py
xseof/aux_orbdop/eo_oper_aux_orbdop_0102.py
xseof/aux_orbdop/eo_oper_aux_orbdop_0103.py
xseof/aux_orbdop/eo_oper_aux_orbdop_0104.py
xseof/aux_orbdop/eo_oper_aux_orbdop_0105.py
xseof/aux_orbdop/eo_oper_aux_orbdop_0200.py
xseof/aux_orbdop/eo_oper_aux_orbdop_0201.py
xseof/aux_orbdop/eo_oper_aux_orbdop_0202.py
xseof/aux_orbdop/eo_oper_aux_orbdop_0203.py
xseof/aux_orbdop/eo_oper_aux_orbdop_0300.py
xseof/aux_orbdop/eo_oper_aux_orbdop_data_block_types_0100.py
xseof/aux_orbdop/eo_oper_aux_orbdop_data_block_types_0101.py
xseof/aux_orbdop/eo_oper_aux_orbdop_data_block_types_0102.py
xseof/aux_orbdop/eo_oper_aux_orbdop_data_block_types_0200.py
xseof/aux_orbdop/eo_oper_aux_orbdop_data_block_types_0201.py
xseof/aux_orbdop/eo_oper_aux_orbdop_data_block_types_0202.py
xseof/aux_orbdop/eo_oper_aux_orbdop_data_block_types_0300.py
xseof/aux_orbdop/eo_oper_aux_orbdop_header_types_0100.py
xseof/aux_orbdop/eo_oper_aux_orbdop_header_types_0101.py
xseof/aux_orbdop/eo_oper_aux_orbdop_header_types_0102.py
xseof/aux_orbdop/eo_oper_aux_orbdop_header_types_0103.py
xseof/aux_orbdop/eo_oper_aux_orbdop_header_types_0200.py
xseof/aux_orbdop/eo_oper_aux_orbdop_header_types_0201.py
xseof/aux_orbdop/eo_oper_aux_orbdop_header_types_0202.py
xseof/aux_orbdop/eo_oper_aux_orbdop_header_types_0300.py
xseof/aux_orbdop/eo_oper_mpl_orbpre_data_block_types_0100.py
xseof/aux_orbdor/__init__.py
xseof/aux_orbdor/eo_oper_aux_orbdor_0100.py
xseof/aux_orbdor/eo_oper_aux_orbdor_0101.py
xseof/aux_orbdor/eo_oper_aux_orbdor_0102.py
xseof/aux_orbdor/eo_oper_aux_orbdor_0103.py
xseof/aux_orbdor/eo_oper_aux_orbdor_0104.py
xseof/aux_orbdor/eo_oper_aux_orbdor_0105.py
xseof/aux_orbdor/eo_oper_aux_orbdor_0200.py
xseof/aux_orbdor/eo_oper_aux_orbdor_0201.py
xseof/aux_orbdor/eo_oper_aux_orbdor_0202.py
xseof/aux_orbdor/eo_oper_aux_orbdor_0203.py
xseof/aux_orbdor/eo_oper_aux_orbdor_0300.py
xseof-1.1.1.dist-info/LICENSE.txt
xseof-1.1.1.dist-info/METADATA
xseof-1.1.1.dist-info/WHEEL
xseof-1.1.1.dist-info/top_level.txt
xseof-1.1.1.dist-info/zip-safe
xseof-1.1.1.dist-info/RECORD
