Metadata-Version: 2.1
Name: xseof
Version: 1.1.1
Summary: I/O library for the ESA EOF files.
Author: Antonio Valentino
License: Apache License 2.0
Project-URL: Source, https://github.com/avalentino/xseof
Project-URL: Tracker, https://github.com/avalentino/xseof/issues
Project-URL: Documentation, https://github.com/avalentino/xseof/blob/main/README.rst
Project-URL: Changelog, https://github.com/avalentino/xseof/blob/main/NEWS.rst
Project-URL: Download, https://pypi.org/project/xseof
Keywords: orbit,attitude,dataclasses
Platform: any
Classifier: Development Status :: 4 - Beta
Classifier: Intended Audience :: Developers
Classifier: Intended Audience :: Science/Research
Classifier: License :: OSI Approved :: Apache Software License
Classifier: Operating System :: OS Independent
Classifier: Programming Language :: Python :: 3
Classifier: Programming Language :: Python :: 3 :: Only
Classifier: Topic :: Scientific/Engineering
Classifier: Topic :: Software Development :: Libraries :: Python Modules
Requires-Python: >=3.6
License-File: LICENSE.txt
Requires-Dist: xsdata
Provides-Extra: podhub
Requires-Dist: lxml ; extra == 'podhub'
